notexbook/__init__.py
notexbook/magic.py
notexbook/settings.py
notexbook/resources/.DS_Store
notexbook/resources/dataframe.css
notexbook/resources/dataframe_css.jinja2
notexbook/resources/editors.css
notexbook/resources/editors_css.jinja2
notexbook/resources/editors_template.jinja2
notexbook/resources/fonts.css
notexbook/resources/fonts_css.jinja2
notexbook/resources/html_export_jupyter_light.css
notexbook/resources/jupyter_light.css
notexbook/resources/jupyter_light_css.jinja2
notexbook/resources/noTeXbook_theme_css.jinja2
notexbook/resources/noTeXbook_theme_template.jinja2
notexbook/resources/notebook.css
notexbook/resources/themes/code_crisp_theme.css
notexbook/resources/themes/code_github2_theme.css
notexbook/resources/themes/code_github_light_theme.css
notexbook/resources/themes/code_github_theme.css
notexbook/resources/themes/code_material_theme.css
notexbook/resources/themes/md_material_theme.css
notexbook/resources/themes/md_typora_theme.css
notexbook/templates/noTeXbook_theme.html
notexbook_theme-2.0.1.dist-info/LICENSE
notexbook_theme-2.0.1.dist-info/METADATA
notexbook_theme-2.0.1.dist-info/WHEEL
notexbook_theme-2.0.1.dist-info/top_level.txt
notexbook_theme-2.0.1.dist-info/RECORD
