Metadata-Version: 2.1
Name: notexbook-theme
Version: 2.0.1
Summary: noTeXbook is a Jupyter notebook theme for Latex lovers ❤
Home-page: https://github.com/leriomaggio/notexbook-jupyter-theme/
Author: Valerio Maggio
Author-email: valeriomaggio@gmail.com
License: UNKNOWN
Platform: UNKNOWN
Classifier: License :: OSI Approved :: Apache Software License
Classifier: Development Status :: 5 - Production/Stable
Classifier: Framework :: IPython
Classifier: Intended Audience :: Developers
Classifier: Intended Audience :: Science/Research
Classifier: Programming Language :: Python :: 3
Classifier: Programming Language :: Python :: 3.4
Classifier: Programming Language :: Python :: 3.5
Classifier: Programming Language :: Python :: 3.6
Classifier: Programming Language :: Python :: 3.7
Classifier: Programming Language :: Python :: 3.8
Requires-Dist: notebook
Requires-Dist: ipython (>=7.0)
Requires-Dist: jupyter
Requires-Dist: jinja2
